{
  "project_info": {
    "project_number": "854323425553",
    "firebase_url": "https://unipractice-bcd90-default-rtdb.firebaseio.com",
    "project_id": "unipractice-bcd90",
    "storage_bucket": "unipractice-bcd90.appspot.com"
  },
  "client": [
    {
      "client_info": {
        "mobilesdk_app_id": "1:854323425553:android:cf2d7a062facc5a6e6dcb0",
        "android_client_info": {
          "package_name": "com.wellness.vet.app"
        }
      },
      "oauth_client": [],
      "api_key": [
        {
          "current_key": "AIzaSyD-sruZGAL91j7J448RHHJRs8Sc_OYL37E"
        }
      ],
      "services": {
        "appinvite_service": {
          "other_platform_oauth_client": []
        }
      }
    }
  ],
  "configuration_version": "1"
}